gnep_learn.py
gnep_learn-0.1.0.dist-info/LICENSE
gnep_learn-0.1.0.dist-info/METADATA
gnep_learn-0.1.0.dist-info/WHEEL
gnep_learn-0.1.0.dist-info/top_level.txt
gnep_learn-0.1.0.dist-info/RECORD
