Metadata-Version: 2.1
Name: gnep-learn
Version: 0.1.0
Summary: gnep-learn - A Python package for learning-based solutions of generalized Nash equilibrium problems.
Author-email: Alberto Bemporad <alberto.bemporad@imtlucca.it>
Project-URL: Homepage, http://cse.lab.imtlucca.it/~bemporad/gnep-learn
Keywords: active learning,generalized nash equilibrium problems,game theory,kalman filtering
Classifier: Programming Language :: Python :: 3
Classifier: License :: OSI Approved :: Apache Software License
Classifier: Operating System :: OS Independent
Requires-Python: >=3.9
License-File: LICENSE
Requires-Dist: numpy
Requires-Dist: scipy
Requires-Dist: cvxopt
Requires-Dist: jax
Requires-Dist: jaxopt
Requires-Dist: tqdm
Requires-Dist: numba
Requires-Dist: joblib
Requires-Dist: matplotlib
